datalad_osf/__init__.py
datalad_osf/_version.py
datalad_osf/annex_remote.py
datalad_osf/conftest.py
datalad_osf/create_sibling_osf.py
datalad_osf/credentials.py
datalad_osf/git_remote.py
datalad_osf/utils.py
datalad_osf/tests/__init__.py
datalad_osf/tests/fixtures.py
datalad_osf/tests/test_create_sibling_osf.py
datalad_osf/tests/test_public.py
datalad_osf/tests/test_register.py
datalad_osf/tests/test_remote.py
datalad_osf/tests/utils.py
datalad_osf-0.3.0.dist-info/LICENSE
datalad_osf-0.3.0.dist-info/METADATA
datalad_osf-0.3.0.dist-info/WHEEL
datalad_osf-0.3.0.dist-info/entry_points.txt
datalad_osf-0.3.0.dist-info/top_level.txt
datalad_osf-0.3.0.dist-info/RECORD
