Metadata-Version: 2.1
Name: datalad-osf
Version: 0.3.0
Summary: DataLad extension to interface with the Open Science Framework (OSF)
Home-page: https://github.com/datalad/datalad-osf
Author: The DataLad Team and Contributors
Author-email: team@datalad.org
License: MIT
Classifier: Programming Language :: Python
Classifier: License :: OSI Approved :: BSD License
Classifier: Programming Language :: Python :: 3
Requires-Python: >=3.7
License-File: LICENSE
Requires-Dist: annexremote (>=1.5.0)
Requires-Dist: datalad (>=0.18.4)
Requires-Dist: datalad-next (>=1.0.0b3)
Requires-Dist: osfclient (>=0.0.5)
Provides-Extra: devel
Requires-Dist: coverage ; extra == 'devel'
Requires-Dist: pytest ; extra == 'devel'
Requires-Dist: pytest-cov ; extra == 'devel'
